<?xml version="1.0" encoding="utf-8"?>
<rdf:RDF xmlns:rdf="http://www.w3.org/1999/02/22-rdf-syntax-ns#" xmlns="http://purl.org/rss/1.0/" xmlns:taxo="http://purl.org/rss/1.0/modules/taxonomy/" 	xmlns:dc="http://purl.org/dc/elements/1.1/" xmlns:syn="http://purl.org/rss/1.0/modules/syndication/">
<channel rdf:about="http://www3.asahi.com/">
 <title>社会 - 朝日新聞デジタル</title>
 <link>https://www.asahi.com/</link>
 <description>朝日新聞のニュースサイト、朝日新聞デジタルの一般社会ニュース、事件・事故、災害・交通情報、裁判、環境などのページです。</description>
 <dc:language>ja</dc:language>
 <dc:rights>Copyright 2024 Asahi Shimbun. All rights reserved. No reproduction or republication without written permission.</dc:rights>
 <dc:date>2024-08-08T21:43:09+09:00</dc:date>
 <dc:publisher>朝日新聞社</dc:publisher>
 <dc:creator>朝日新聞社</dc:creator>
 <syn:updatePeriod>hourly</syn:updatePeriod>
 <syn:updateFrequency>1</syn:updateFrequency>
 <syn:updateBase>2024-08-08T21:43:09+09:00</syn:updateBase>
 <items>
  <rdf:Seq>
   <rdf:li rdf:resource="https://www.asahi.com/articles/ASS8815JNS88DIFI013M.html?ref=rss"/>
   <rdf:li rdf:resource="https://www.asahi.com/articles/ASS883V7ZS88UTIL01GM.html?ref=rss"/>
   <rdf:li rdf:resource="https://www.asahi.com/articles/ASS883TGPS88UOOB011M.html?ref=rss"/>
   <rdf:li rdf:resource="https://www.asahi.com/articles/ASS882TYWS88DIFI011M.html?ref=rss"/>
   <rdf:li rdf:resource="https://www.asahi.com/articles/ASS883TKRS88PIHB00PM.html?ref=rss"/>
   <rdf:li rdf:resource="https://www.asahi.com/articles/ASS883S6YS88UGTB00KM.html?ref=rss"/>
   <rdf:li rdf:resource="https://www.asahi.com/articles/ASS883JPHS88UTIL01CM.html?ref=rss"/>
   <rdf:li rdf:resource="https://www.asahi.com/articles/ASS883442S88IIPE00WM.html?ref=rss"/>
   <rdf:li rdf:resource="https://www.asahi.com/articles/ASS883GJ7S88PLBJ006M.html?ref=rss"/>
   <rdf:li rdf:resource="https://www.asahi.com/articles/ASS883DZRS88ULBH00DM.html?ref=rss"/>
   <rdf:li rdf:resource="https://www.asahi.com/articles/ASS883FNMS88UTIL02NM.html?ref=rss"/>
   <rdf:li rdf:resource="https://www.asahi.com/articles/ASS882HS2S88DIFI00MM.html?ref=rss"/>
   <rdf:li rdf:resource="https://www.asahi.com/articles/ASS882VXLS88IIPE005M.html?ref=rss"/>
   <rdf:li rdf:resource="https://www.asahi.com/articles/ASS88368MS88UTFL018M.html?ref=rss"/>
   <rdf:li rdf:resource="https://www.asahi.com/articles/ASS88327DS88UTIL01MM.html?ref=rss"/>
   <rdf:li rdf:resource="https://www.asahi.com/articles/ASS882TFHS88UTIL01SM.html?ref=rss"/>
   <rdf:li rdf:resource="https://www.asahi.com/articles/ASS881JD4S88OXIE05XM.html?ref=rss"/>
   <rdf:li rdf:resource="https://www.asahi.com/articles/ASS882CPCS88OXIE02FM.html?ref=rss"/>
   <rdf:li rdf:resource="https://www.asahi.com/articles/ASS882TW0S88ULBH008M.html?ref=rss"/>
   <rdf:li rdf:resource="https://www.asahi.com/articles/ASS882JGRS88UTIL01DM.html?ref=rss"/>
   <rdf:li rdf:resource="https://www.asahi.com/articles/ASS882SSFS88ULBH009M.html?ref=rss"/>
   <rdf:li rdf:resource="https://www.asahi.com/articles/ASS8825RFS88PITB008M.html?ref=rss"/>
   <rdf:li rdf:resource="https://www.asahi.com/articles/ASS882Q00S88UTIL00CM.html?ref=rss"/>
   <rdf:li rdf:resource="https://www.asahi.com/articles/ASS79354QS79UTIL00LM.html?ref=rss"/>
   <rdf:li rdf:resource="https://www.asahi.com/articles/ASS877VRMS87UTIL01ZM.html?ref=rss"/>
   <rdf:li rdf:resource="https://www.asahi.com/articles/ASS877SRNS87UTIL008M.html?ref=rss"/>
   <rdf:li rdf:resource="https://www.asahi.com/articles/ASS880V7CS88TLVB005M.html?ref=rss"/>
   <rdf:li rdf:resource="https://www.asahi.com/articles/ASS881TG7S88PQIP04VM.html?ref=rss"/>
   <rdf:li rdf:resource="https://www.asahi.com/articles/ASS8825N1S88TOLB004M.html?ref=rss"/>
   <rdf:li rdf:resource="https://www.asahi.com/articles/ASS88226RS88PIHB003M.html?ref=rss"/>
   <rdf:li rdf:resource="https://www.asahi.com/articles/ASS8826HVS88UTIL01BM.html?ref=rss"/>
   <rdf:li rdf:resource="https://www.asahi.com/articles/ASS8826HGS88UTNB009M.html?ref=rss"/>
   <rdf:li rdf:resource="https://www.asahi.com/articles/ASS847X21S84PLPB007M.html?ref=rss"/>
   <rdf:li rdf:resource="https://www.asahi.com/articles/ASS881SQNS88TIPE00BM.html?ref=rss"/>
   <rdf:li rdf:resource="https://www.asahi.com/articles/ASS881QJVS88UTIL00CM.html?ref=rss"/>
   <rdf:li rdf:resource="https://www.asahi.com/articles/ASS881J2CS88UTIL00DM.html?ref=rss"/>
   <rdf:li rdf:resource="https://www.asahi.com/articles/ASS87471GS87PTIL013M.html?ref=rss"/>
   <rdf:li rdf:resource="https://www.asahi.com/articles/ASS8812NDS88PLXB005M.html?ref=rss"/>
   <rdf:li rdf:resource="https://www.asahi.com/articles/ASS8731CYS87PLXB009M.html?ref=rss"/>
   <rdf:li rdf:resource="https://www.asahi.com/articles/ASS8811QDS88UTIL006M.html?ref=rss"/>
  </rdf:Seq>
 </items>
</channel>
<item rdf:about="https://www.asahi.com/articles/ASS8815JNS88DIFI013M.html?ref=rss">
 <title>【速報中】ドイツ献花、イタリアは欠席　長崎市に電話「賛同が多い」</title>
 <link>https://www.asahi.com/articles/ASS8815JNS88DIFI013M.html?ref=rss</link>
 <description></description>
 <dc:subject>社会</dc:subject>
 <dc:date>2024-08-08T21:43:09+09:00</dc:date>
</item>
<item rdf:about="https://www.asahi.com/articles/ASS883V7ZS88UTIL01GM.html?ref=rss">
 <title>ウソの供述「誘発しかねない」　高裁が批判した特捜検事、刑事裁判へ</title>
 <link>https://www.asahi.com/articles/ASS883V7ZS88UTIL01GM.html?ref=rss</link>
 <description></description>
 <dc:subject>社会</dc:subject>
 <dc:date>2024-08-08T21:22:16+09:00</dc:date>
</item>
<item rdf:about="https://www.asahi.com/articles/ASS883TGPS88UOOB011M.html?ref=rss">
 <title>ライトアップされた松本城で薪能　夜風の中、鼓や笛が響く優雅な演目</title>
 <link>https://www.asahi.com/articles/ASS883TGPS88UOOB011M.html?ref=rss</link>
 <description></description>
 <dc:subject>社会</dc:subject>
 <dc:date>2024-08-08T21:15:00+09:00</dc:date>
</item>
<item rdf:about="https://www.asahi.com/articles/ASS882TYWS88DIFI011M.html?ref=rss">
 <title>【速報中】東海道新幹線、三島―三河安城間で1週間ほど減速運転</title>
 <link>https://www.asahi.com/articles/ASS882TYWS88DIFI011M.html?ref=rss</link>
 <description></description>
 <dc:subject>社会</dc:subject>
 <dc:date>2024-08-08T21:11:25+09:00</dc:date>
</item>
<item rdf:about="https://www.asahi.com/articles/ASS883TKRS88PIHB00PM.html?ref=rss">
 <title>市営プールで小学生がおぼれ重体　兵庫・加古川「浜の宮市民プール」</title>
 <link>https://www.asahi.com/articles/ASS883TKRS88PIHB00PM.html?ref=rss</link>
 <description></description>
 <dc:subject>社会</dc:subject>
 <dc:date>2024-08-08T21:11:19+09:00</dc:date>
</item>
<item rdf:about="https://www.asahi.com/articles/ASS883S6YS88UGTB00KM.html?ref=rss">
 <title>福島空港の工事巡る収賄の罪で福島県主査を在宅起訴、課長も略式起訴</title>
 <link>https://www.asahi.com/articles/ASS883S6YS88UGTB00KM.html?ref=rss</link>
 <description></description>
 <dc:subject>社会</dc:subject>
 <dc:date>2024-08-08T20:37:00+09:00</dc:date>
</item>
<item rdf:about="https://www.asahi.com/articles/ASS883JPHS88UTIL01CM.html?ref=rss">
 <title>「マジ！？」検察に衝撃が走った　「裁判所との全面戦争になる」</title>
 <link>https://www.asahi.com/articles/ASS883JPHS88UTIL01CM.html?ref=rss</link>
 <description></description>
 <dc:subject>社会</dc:subject>
 <dc:date>2024-08-08T20:01:17+09:00</dc:date>
</item>
<item rdf:about="https://www.asahi.com/articles/ASS883442S88IIPE00WM.html?ref=rss">
 <title>発達障害を理由に雇い止め、北海道大学と原告の和解が成立　札幌地裁</title>
 <link>https://www.asahi.com/articles/ASS883442S88IIPE00WM.html?ref=rss</link>
 <description></description>
 <dc:subject>社会</dc:subject>
 <dc:date>2024-08-08T20:00:00+09:00</dc:date>
</item>
<item rdf:about="https://www.asahi.com/articles/ASS883GJ7S88PLBJ006M.html?ref=rss">
 <title>臨時情報後により大きな地震、頻度は数百回に1回　備えの点検を</title>
 <link>https://www.asahi.com/articles/ASS883GJ7S88PLBJ006M.html?ref=rss</link>
 <description></description>
 <dc:subject>社会</dc:subject>
 <dc:date>2024-08-08T19:57:46+09:00</dc:date>
</item>
<item rdf:about="https://www.asahi.com/articles/ASS883DZRS88ULBH00DM.html?ref=rss">
 <title>日向灘地震は「プレート境界型」　南海トラフ全域への影響は限定的か</title>
 <link>https://www.asahi.com/articles/ASS883DZRS88ULBH00DM.html?ref=rss</link>
 <description></description>
 <dc:subject>社会</dc:subject>
 <dc:date>2024-08-08T19:48:35+09:00</dc:date>
</item>
<item rdf:about="https://www.asahi.com/articles/ASS883FNMS88UTIL02NM.html?ref=rss">
 <title>南海トラフ地震「注意」、気象庁が臨時情報　今後1週間は備えを</title>
 <link>https://www.asahi.com/articles/ASS883FNMS88UTIL02NM.html?ref=rss</link>
 <description></description>
 <dc:subject>社会</dc:subject>
 <dc:date>2024-08-08T19:41:04+09:00</dc:date>
</item>
<item rdf:about="https://www.asahi.com/articles/ASS882HS2S88DIFI00MM.html?ref=rss">
 <title>宮崎県日南市で震度6弱　8日午後7時現在、宮崎県に津波注意報</title>
 <link>https://www.asahi.com/articles/ASS882HS2S88DIFI00MM.html?ref=rss</link>
 <description></description>
 <dc:subject>社会</dc:subject>
 <dc:date>2024-08-08T19:30:25+09:00</dc:date>
</item>
<item rdf:about="https://www.asahi.com/articles/ASS882VXLS88IIPE005M.html?ref=rss">
 <title>「裁判所の予算で手話通訳を」　障害者虐待めぐる訴訟で原告側が要請</title>
 <link>https://www.asahi.com/articles/ASS882VXLS88IIPE005M.html?ref=rss</link>
 <description></description>
 <dc:subject>社会</dc:subject>
 <dc:date>2024-08-08T19:30:00+09:00</dc:date>
</item>
<item rdf:about="https://www.asahi.com/articles/ASS88368MS88UTFL018M.html?ref=rss">
 <title>学童保育の待機児童問題　加藤こども相「利用制限は考えていない」</title>
 <link>https://www.asahi.com/articles/ASS88368MS88UTFL018M.html?ref=rss</link>
 <description></description>
 <dc:subject>社会</dc:subject>
 <dc:date>2024-08-08T19:08:41+09:00</dc:date>
</item>
<item rdf:about="https://www.asahi.com/articles/ASS88327DS88UTIL01MM.html?ref=rss">
 <title>サッカー元日本代表・佐野海舟選手を不起訴に　不同意性交容疑で逮捕</title>
 <link>https://www.asahi.com/articles/ASS88327DS88UTIL01MM.html?ref=rss</link>
 <description></description>
 <dc:subject>社会</dc:subject>
 <dc:date>2024-08-08T18:30:06+09:00</dc:date>
</item>
<item rdf:about="https://www.asahi.com/articles/ASS882TFHS88UTIL01SM.html?ref=rss">
 <title>大阪高裁が大阪地検を痛烈批判　元特捜検事の刑事裁判決めた決定要旨</title>
 <link>https://www.asahi.com/articles/ASS882TFHS88UTIL01SM.html?ref=rss</link>
 <description></description>
 <dc:subject>社会</dc:subject>
 <dc:date>2024-08-08T18:08:00+09:00</dc:date>
</item>
<item rdf:about="https://www.asahi.com/articles/ASS881JD4S88OXIE05XM.html?ref=rss">
 <title>7月降水量、東京都心は前年の7倍　相次ぐ豪雨、「垂直避難」訓練も</title>
 <link>https://www.asahi.com/articles/ASS881JD4S88OXIE05XM.html?ref=rss</link>
 <description></description>
 <dc:subject>社会</dc:subject>
 <dc:date>2024-08-08T18:00:00+09:00</dc:date>
</item>
<item rdf:about="https://www.asahi.com/articles/ASS882CPCS88OXIE02FM.html?ref=rss">
 <title>検事について初の付審判決定、どんな制度？　過去には無罪判決の例も</title>
 <link>https://www.asahi.com/articles/ASS882CPCS88OXIE02FM.html?ref=rss</link>
 <description></description>
 <dc:subject>社会</dc:subject>
 <dc:date>2024-08-08T18:00:00+09:00</dc:date>
</item>
<item rdf:about="https://www.asahi.com/articles/ASS882TW0S88ULBH008M.html?ref=rss">
 <title>南海トラフ地震の臨時情報って何？　最短2時間で調査結果発表</title>
 <link>https://www.asahi.com/articles/ASS882TW0S88ULBH008M.html?ref=rss</link>
 <description></description>
 <dc:subject>社会</dc:subject>
 <dc:date>2024-08-08T17:49:53+09:00</dc:date>
</item>
<item rdf:about="https://www.asahi.com/articles/ASS882JGRS88UTIL01DM.html?ref=rss">
 <title>「ガキ」「検察庁敵視は反社」　検事の取り調べ、相次ぐ国賠訴訟</title>
 <link>https://www.asahi.com/articles/ASS882JGRS88UTIL01DM.html?ref=rss</link>
 <description></description>
 <dc:subject>社会</dc:subject>
 <dc:date>2024-08-08T17:43:57+09:00</dc:date>
</item>
<item rdf:about="https://www.asahi.com/articles/ASS882SSFS88ULBH009M.html?ref=rss">
 <title>日向灘震源の地震、川内原発と伊方原発は「異常なし」　原子力規制委</title>
 <link>https://www.asahi.com/articles/ASS882SSFS88ULBH009M.html?ref=rss</link>
 <description></description>
 <dc:subject>社会</dc:subject>
 <dc:date>2024-08-08T17:37:32+09:00</dc:date>
</item>
<item rdf:about="https://www.asahi.com/articles/ASS8825RFS88PITB008M.html?ref=rss">
 <title>猛暑のせい？広島の夏の交通事故、死者数が倍に　警察が注意呼びかけ</title>
 <link>https://www.asahi.com/articles/ASS8825RFS88PITB008M.html?ref=rss</link>
 <description></description>
 <dc:subject>社会</dc:subject>
 <dc:date>2024-08-08T17:30:00+09:00</dc:date>
</item>
<item rdf:about="https://www.asahi.com/articles/ASS882Q00S88UTIL00CM.html?ref=rss">
 <title>日向灘の地震、南海トラフ地震との関連を調査　気象庁が「臨時情報」</title>
 <link>https://www.asahi.com/articles/ASS882Q00S88UTIL00CM.html?ref=rss</link>
 <description></description>
 <dc:subject>社会</dc:subject>
 <dc:date>2024-08-08T17:18:35+09:00</dc:date>
</item>
<item rdf:about="https://www.asahi.com/articles/ASS79354QS79UTIL00LM.html?ref=rss">
 <title>医師の治療「もっと早く」　中2で受けた性暴力が長く私を苦しめる</title>
 <link>https://www.asahi.com/articles/ASS79354QS79UTIL00LM.html?ref=rss</link>
 <description></description>
 <dc:subject>社会</dc:subject>
 <dc:date>2024-08-08T17:00:00+09:00</dc:date>
</item>
<item rdf:about="https://www.asahi.com/articles/ASS877VRMS87UTIL01ZM.html?ref=rss">
 <title>散在する日本語指導が必要な子　「学校に1人」をどう支える?</title>
 <link>https://www.asahi.com/articles/ASS877VRMS87UTIL01ZM.html?ref=rss</link>
 <description></description>
 <dc:subject>社会</dc:subject>
 <dc:date>2024-08-08T17:00:00+09:00</dc:date>
</item>
<item rdf:about="https://www.asahi.com/articles/ASS877SRNS87UTIL008M.html?ref=rss">
 <title>日本語指導が必要な子、過去最多6万9千人　支援追いつかず</title>
 <link>https://www.asahi.com/articles/ASS877SRNS87UTIL008M.html?ref=rss</link>
 <description></description>
 <dc:subject>社会</dc:subject>
 <dc:date>2024-08-08T17:00:00+09:00</dc:date>
</item>
<item rdf:about="https://www.asahi.com/articles/ASS880V7CS88TLVB005M.html?ref=rss">
 <title>ヒゴタイ、ユウスゲ…咲き誇る高原にブルービーも舞う　阿蘇・産山</title>
 <link>https://www.asahi.com/articles/ASS880V7CS88TLVB005M.html?ref=rss</link>
 <description></description>
 <dc:subject>社会</dc:subject>
 <dc:date>2024-08-08T17:00:00+09:00</dc:date>
</item>
<item rdf:about="https://www.asahi.com/articles/ASS881TG7S88PQIP04VM.html?ref=rss">
 <title>頭そりあげ→短髪？変装して押し入ったか　ミナミ宝飾店強盗の容疑者</title>
 <link>https://www.asahi.com/articles/ASS881TG7S88PQIP04VM.html?ref=rss</link>
 <description></description>
 <dc:subject>社会</dc:subject>
 <dc:date>2024-08-08T16:38:50+09:00</dc:date>
</item>
<item rdf:about="https://www.asahi.com/articles/ASS8825N1S88TOLB004M.html?ref=rss">
 <title>米英などの式典欠席「私の真意伝わらず」　長崎・鈴木市長の一問一答</title>
 <link>https://www.asahi.com/articles/ASS8825N1S88TOLB004M.html?ref=rss</link>
 <description></description>
 <dc:subject>社会</dc:subject>
 <dc:date>2024-08-08T16:29:21+09:00</dc:date>
</item>
<item rdf:about="https://www.asahi.com/articles/ASS88226RS88PIHB003M.html?ref=rss">
 <title>「取調室で『吐け』と自白強要」 誤認逮捕され提訴の女性が意見陳述</title>
 <link>https://www.asahi.com/articles/ASS88226RS88PIHB003M.html?ref=rss</link>
 <description></description>
 <dc:subject>社会</dc:subject>
 <dc:date>2024-08-08T16:28:36+09:00</dc:date>
</item>
<item rdf:about="https://www.asahi.com/articles/ASS8826HVS88UTIL01BM.html?ref=rss">
 <title>「休憩」も労働認定、未払い最大86億円か　東京地下鉄に是正勧告</title>
 <link>https://www.asahi.com/articles/ASS8826HVS88UTIL01BM.html?ref=rss</link>
 <description></description>
 <dc:subject>社会</dc:subject>
 <dc:date>2024-08-08T16:19:24+09:00</dc:date>
</item>
<item rdf:about="https://www.asahi.com/articles/ASS8826HGS88UTNB009M.html?ref=rss">
 <title>埼玉・川口のマンション爆発、住人の中国籍男を逮捕　激発物破裂容疑</title>
 <link>https://www.asahi.com/articles/ASS8826HGS88UTNB009M.html?ref=rss</link>
 <description></description>
 <dc:subject>社会</dc:subject>
 <dc:date>2024-08-08T16:13:00+09:00</dc:date>
</item>
<item rdf:about="https://www.asahi.com/articles/ASS847X21S84PLPB007M.html?ref=rss">
 <title>赤ちゃん泣いた、その気持ち　精度87%で分かるAIアプリが登場</title>
 <link>https://www.asahi.com/articles/ASS847X21S84PLPB007M.html?ref=rss</link>
 <description></description>
 <dc:subject>社会</dc:subject>
 <dc:date>2024-08-08T16:00:00+09:00</dc:date>
</item>
<item rdf:about="https://www.asahi.com/articles/ASS881SQNS88TIPE00BM.html?ref=rss">
 <title>高校生の男女、50歳男性を殺人未遂の疑い　「元カレ殺そうとした」</title>
 <link>https://www.asahi.com/articles/ASS881SQNS88TIPE00BM.html?ref=rss</link>
 <description></description>
 <dc:subject>社会</dc:subject>
 <dc:date>2024-08-08T15:07:11+09:00</dc:date>
</item>
<item rdf:about="https://www.asahi.com/articles/ASS881QJVS88UTIL00CM.html?ref=rss">
 <title>損保大手4社に独禁法違反の疑い　公取委が課徴金19億円命令の方針</title>
 <link>https://www.asahi.com/articles/ASS881QJVS88UTIL00CM.html?ref=rss</link>
 <description></description>
 <dc:subject>社会</dc:subject>
 <dc:date>2024-08-08T15:00:00+09:00</dc:date>
</item>
<item rdf:about="https://www.asahi.com/articles/ASS881J2CS88UTIL00DM.html?ref=rss">
 <title>ラブホテル客室侵入、寝ている女性触った疑い　アルバイト逮捕　渋谷</title>
 <link>https://www.asahi.com/articles/ASS881J2CS88UTIL00DM.html?ref=rss</link>
 <description></description>
 <dc:subject>社会</dc:subject>
 <dc:date>2024-08-08T14:54:34+09:00</dc:date>
</item>
<item rdf:about="https://www.asahi.com/articles/ASS87471GS87PTIL013M.html?ref=rss">
 <title>「検察なめんな」発言の特捜検事、刑事裁判へ　元社長無罪の事件</title>
 <link>https://www.asahi.com/articles/ASS87471GS87PTIL013M.html?ref=rss</link>
 <description></description>
 <dc:subject>社会</dc:subject>
 <dc:date>2024-08-08T14:15:00+09:00</dc:date>
</item>
<item rdf:about="https://www.asahi.com/articles/ASS8812NDS88PLXB005M.html?ref=rss">
 <title>日下尚の金メダルに未明の体育館は歓喜の渦　コーチや後輩、市長まで</title>
 <link>https://www.asahi.com/articles/ASS8812NDS88PLXB005M.html?ref=rss</link>
 <description></description>
 <dc:subject>社会</dc:subject>
 <dc:date>2024-08-08T14:05:00+09:00</dc:date>
</item>
<item rdf:about="https://www.asahi.com/articles/ASS8731CYS87PLXB009M.html?ref=rss">
 <title>よさこい祭りに性的少数者らが新チーム　「多様な生き方広げたい」</title>
 <link>https://www.asahi.com/articles/ASS8731CYS87PLXB009M.html?ref=rss</link>
 <description></description>
 <dc:subject>社会</dc:subject>
 <dc:date>2024-08-08T14:00:00+09:00</dc:date>
</item>
<item rdf:about="https://www.asahi.com/articles/ASS8811QDS88UTIL006M.html?ref=rss">
 <title>オンラインゲーム通貨詐取容疑で男逮捕　「課金代行」で3千万円超か</title>
 <link>https://www.asahi.com/articles/ASS8811QDS88UTIL006M.html?ref=rss</link>
 <description></description>
 <dc:subject>社会</dc:subject>
 <dc:date>2024-08-08T12:43:23+09:00</dc:date>
</item>
</rdf:RDF>
