<?xml version="1.0" encoding="utf-8"?>
<rdf:RDF xmlns:rdf="http://www.w3.org/1999/02/22-rdf-syntax-ns#" xmlns="http://purl.org/rss/1.0/" xmlns:taxo="http://purl.org/rss/1.0/modules/taxonomy/" 	xmlns:dc="http://purl.org/dc/elements/1.1/" xmlns:syn="http://purl.org/rss/1.0/modules/syndication/">
<channel rdf:about="http://www3.asahi.com/">
 <title>政治 - 朝日新聞デジタル</title>
 <link>https://www.asahi.com/</link>
 <description>朝日新聞のニュースサイト、朝日新聞デジタルの一般政治ニュース、国政、地方政治内閣支持率などに関するページです。</description>
 <dc:language>ja</dc:language>
 <dc:rights>Copyright 2024 Asahi Shimbun. All rights reserved. No reproduction or republication without written permission.</dc:rights>
 <dc:date>2024-09-13T20:30:00+09:00</dc:date>
 <dc:publisher>朝日新聞社</dc:publisher>
 <dc:creator>朝日新聞社</dc:creator>
 <syn:updatePeriod>hourly</syn:updatePeriod>
 <syn:updateFrequency>1</syn:updateFrequency>
 <syn:updateBase>2024-09-13T20:30:00+09:00</syn:updateBase>
 <items>
  <rdf:Seq>
   <rdf:li rdf:resource="https://www.asahi.com/articles/ASS9F3PSFS9FUTFK006M.html?ref=rss"/>
   <rdf:li rdf:resource="https://www.asahi.com/articles/ASS9F36MNS9FULFA00JM.html?ref=rss"/>
   <rdf:li rdf:resource="https://www.asahi.com/articles/ASS9F23ZZS9FPITB009M.html?ref=rss"/>
   <rdf:li rdf:resource="https://www.asahi.com/articles/ASS9F1PSYS9FUTIL027M.html?ref=rss"/>
   <rdf:li rdf:resource="https://www.asahi.com/articles/ASS9F23KSS9FUTFK01RM.html?ref=rss"/>
   <rdf:li rdf:resource="https://www.asahi.com/articles/ASS9C1601S9CUZPS001M.html?ref=rss"/>
   <rdf:li rdf:resource="https://www.asahi.com/articles/ASS9D35ZHS9DUPQJ00DM.html?ref=rss"/>
   <rdf:li rdf:resource="https://www.asahi.com/articles/ASS9F0S8FS9FUTFK01QM.html?ref=rss"/>
   <rdf:li rdf:resource="https://www.asahi.com/articles/ASS9D3V5ZS9DUTFK00KM.html?ref=rss"/>
   <rdf:li rdf:resource="https://www.asahi.com/articles/ASS9D2HKYS9DPIHB00RM.html?ref=rss"/>
   <rdf:li rdf:resource="https://www.asahi.com/articles/ASS993TFHS99UZPS00CM.html?ref=rss"/>
   <rdf:li rdf:resource="https://www.asahi.com/articles/ASS9C2HGLS9CUCVL027M.html?ref=rss"/>
   <rdf:li rdf:resource="https://www.asahi.com/articles/ASS9D3TBDS9DUTFK00MM.html?ref=rss"/>
   <rdf:li rdf:resource="https://www.asahi.com/articles/ASS9D3QN5S9DUTIL01DM.html?ref=rss"/>
   <rdf:li rdf:resource="https://www.asahi.com/articles/ASS9D3CL5S9DUTFK00JM.html?ref=rss"/>
   <rdf:li rdf:resource="https://www.asahi.com/articles/ASS9D3CHFS9DUTFK00FM.html?ref=rss"/>
   <rdf:li rdf:resource="https://www.asahi.com/articles/ASS9D046QS9DUTFK02TM.html?ref=rss"/>
   <rdf:li rdf:resource="https://www.asahi.com/articles/ASS9D2C5QS9DUTFK008M.html?ref=rss"/>
   <rdf:li rdf:resource="https://www.asahi.com/articles/ASS9D25ZBS9DULFA010M.html?ref=rss"/>
   <rdf:li rdf:resource="https://www.asahi.com/articles/ASS9D2CXBS9DPIHB009M.html?ref=rss"/>
  </rdf:Seq>
 </items>
</channel>
<item rdf:about="https://www.asahi.com/articles/ASS9F3PSFS9FUTFK006M.html?ref=rss">
 <title>9候補、いずれも裏金事件解明に消極姿勢　自民党総裁選の記者会見</title>
 <link>https://www.asahi.com/articles/ASS9F3PSFS9FUTFK006M.html?ref=rss</link>
 <description></description>
 <dc:subject>政治</dc:subject>
 <dc:date>2024-09-13T20:30:00+09:00</dc:date>
</item>
<item rdf:about="https://www.asahi.com/articles/ASS9F36MNS9FULFA00JM.html?ref=rss">
 <title>小泉氏主張の解雇規制に「すさまじいハレーション」　他候補は慎重論</title>
 <link>https://www.asahi.com/articles/ASS9F36MNS9FULFA00JM.html?ref=rss</link>
 <description></description>
 <dc:subject>政治</dc:subject>
 <dc:date>2024-09-13T19:35:28+09:00</dc:date>
</item>
<item rdf:about="https://www.asahi.com/articles/ASS9F23ZZS9FPITB009M.html?ref=rss">
 <title>「閑古鳥鳴く」総裁選　岸田首相の地元広島に触手伸ばす山口、鳥取…</title>
 <link>https://www.asahi.com/articles/ASS9F23ZZS9FPITB009M.html?ref=rss</link>
 <description></description>
 <dc:subject>政治</dc:subject>
 <dc:date>2024-09-13T18:00:00+09:00</dc:date>
</item>
<item rdf:about="https://www.asahi.com/articles/ASS9F1PSYS9FUTIL027M.html?ref=rss">
 <title>パーティー依存高い候補も　裏金問題焦点の自民総裁選　資金力に差</title>
 <link>https://www.asahi.com/articles/ASS9F1PSYS9FUTIL027M.html?ref=rss</link>
 <description></description>
 <dc:subject>政治</dc:subject>
 <dc:date>2024-09-13T17:46:31+09:00</dc:date>
</item>
<item rdf:about="https://www.asahi.com/articles/ASS9F23KSS9FUTFK01RM.html?ref=rss">
 <title>小泉氏、選択的夫婦別姓は「党一丸で」　採決には党議拘束かけないが</title>
 <link>https://www.asahi.com/articles/ASS9F23KSS9FUTFK01RM.html?ref=rss</link>
 <description></description>
 <dc:subject>政治</dc:subject>
 <dc:date>2024-09-13T17:30:00+09:00</dc:date>
</item>
<item rdf:about="https://www.asahi.com/articles/ASS9C1601S9CUZPS001M.html?ref=rss">
 <title>過去を乗り越え、恩讐を越えて共闘する立憲2人　12年前の世論では</title>
 <link>https://www.asahi.com/articles/ASS9C1601S9CUZPS001M.html?ref=rss</link>
 <description></description>
 <dc:subject>政治</dc:subject>
 <dc:date>2024-09-13T17:00:00+09:00</dc:date>
</item>
<item rdf:about="https://www.asahi.com/articles/ASS9D35ZHS9DUPQJ00DM.html?ref=rss">
 <title>ふたたび「挑戦者の政治」を　混迷から生まれる新たな人材と政策</title>
 <link>https://www.asahi.com/articles/ASS9D35ZHS9DUPQJ00DM.html?ref=rss</link>
 <description></description>
 <dc:subject>政治</dc:subject>
 <dc:date>2024-09-13T16:30:00+09:00</dc:date>
</item>
<item rdf:about="https://www.asahi.com/articles/ASS9F0S8FS9FUTFK01QM.html?ref=rss">
 <title>公明・石井幹事長、代表選出馬を「熟慮」　山口氏の後継として最有力</title>
 <link>https://www.asahi.com/articles/ASS9F0S8FS9FUTFK01QM.html?ref=rss</link>
 <description></description>
 <dc:subject>政治</dc:subject>
 <dc:date>2024-09-13T11:55:00+09:00</dc:date>
</item>
<item rdf:about="https://www.asahi.com/articles/ASS9D3V5ZS9DUTFK00KM.html?ref=rss">
 <title>立憲代表選で｢名義貸し」　4人論戦で多様性演出も｢裏口入学｣の声</title>
 <link>https://www.asahi.com/articles/ASS9D3V5ZS9DUTFK00KM.html?ref=rss</link>
 <description></description>
 <dc:subject>政治</dc:subject>
 <dc:date>2024-09-13T11:30:00+09:00</dc:date>
</item>
<item rdf:about="https://www.asahi.com/articles/ASS9D2HKYS9DPIHB00RM.html?ref=rss">
 <title>兵庫県知事の不信任決議案、19日可決へ　維新も共同提案する方向</title>
 <link>https://www.asahi.com/articles/ASS9D2HKYS9DPIHB00RM.html?ref=rss</link>
 <description></description>
 <dc:subject>政治</dc:subject>
 <dc:date>2024-09-13T11:01:52+09:00</dc:date>
</item>
<item rdf:about="https://www.asahi.com/articles/ASS993TFHS99UZPS00CM.html?ref=rss">
 <title>防災意識は高まったのか、南海トラフ地震の臨時情報を受けて尋ねると</title>
 <link>https://www.asahi.com/articles/ASS993TFHS99UZPS00CM.html?ref=rss</link>
 <description></description>
 <dc:subject>政治</dc:subject>
 <dc:date>2024-09-13T11:00:00+09:00</dc:date>
</item>
<item rdf:about="https://www.asahi.com/articles/ASS9C2HGLS9CUCVL027M.html?ref=rss">
 <title>日本近現代史の開拓と、「右派論客」の顔と　恩師・伊藤隆さんを悼む</title>
 <link>https://www.asahi.com/articles/ASS9C2HGLS9CUCVL027M.html?ref=rss</link>
 <description></description>
 <dc:subject>政治</dc:subject>
 <dc:date>2024-09-13T06:00:00+09:00</dc:date>
</item>
<item rdf:about="https://www.asahi.com/articles/ASS9D3TBDS9DUTFK00MM.html?ref=rss">
 <title>「決選投票では分かっているな」すごむ菅氏　混戦の総裁選、動く重鎮</title>
 <link>https://www.asahi.com/articles/ASS9D3TBDS9DUTFK00MM.html?ref=rss</link>
 <description></description>
 <dc:subject>政治</dc:subject>
 <dc:date>2024-09-13T05:00:00+09:00</dc:date>
</item>
<item rdf:about="https://www.asahi.com/articles/ASS9D3QN5S9DUTIL01DM.html?ref=rss">
 <title>【解説人語】候補者９人で乱戦　過去にない混戦の自民総裁選を解説</title>
 <link>https://www.asahi.com/articles/ASS9D3QN5S9DUTIL01DM.html?ref=rss</link>
 <description></description>
 <dc:subject>政治</dc:subject>
 <dc:date>2024-09-12T21:45:00+09:00</dc:date>
</item>
<item rdf:about="https://www.asahi.com/articles/ASS9D3CL5S9DUTFK00JM.html?ref=rss">
 <title>石破・小泉の2氏が優位、追う高市氏　自民総裁選は決選投票の公算大</title>
 <link>https://www.asahi.com/articles/ASS9D3CL5S9DUTFK00JM.html?ref=rss</link>
 <description></description>
 <dc:subject>政治</dc:subject>
 <dc:date>2024-09-12T19:42:04+09:00</dc:date>
</item>
<item rdf:about="https://www.asahi.com/articles/ASS9D3CHFS9DUTFK00FM.html?ref=rss">
 <title>「野党のまね」「世襲多い」　立憲代表選の4候補、自民総裁選にクギ</title>
 <link>https://www.asahi.com/articles/ASS9D3CHFS9DUTFK00FM.html?ref=rss</link>
 <description></description>
 <dc:subject>政治</dc:subject>
 <dc:date>2024-09-12T19:30:00+09:00</dc:date>
</item>
<item rdf:about="https://www.asahi.com/articles/ASS9D046QS9DUTFK02TM.html?ref=rss">
 <title>【詳報】自民総裁選告示、過去最多9人届け出　裏金問題が最大の焦点</title>
 <link>https://www.asahi.com/articles/ASS9D046QS9DUTFK02TM.html?ref=rss</link>
 <description></description>
 <dc:subject>政治</dc:subject>
 <dc:date>2024-09-12T17:37:29+09:00</dc:date>
</item>
<item rdf:about="https://www.asahi.com/articles/ASS9D2C5QS9DUTFK008M.html?ref=rss">
 <title>自民総裁選、9候補の歩みや人柄は…　15日間の論戦スタート</title>
 <link>https://www.asahi.com/articles/ASS9D2C5QS9DUTFK008M.html?ref=rss</link>
 <description></description>
 <dc:subject>政治</dc:subject>
 <dc:date>2024-09-12T17:00:00+09:00</dc:date>
</item>
<item rdf:about="https://www.asahi.com/articles/ASS9D25ZBS9DULFA010M.html?ref=rss">
 <title>9候補とも裏金解明に後ろ向き　自民総裁選、個別政策の論戦は活発に</title>
 <link>https://www.asahi.com/articles/ASS9D25ZBS9DULFA010M.html?ref=rss</link>
 <description></description>
 <dc:subject>政治</dc:subject>
 <dc:date>2024-09-12T16:55:08+09:00</dc:date>
</item>
<item rdf:about="https://www.asahi.com/articles/ASS9D2CXBS9DPIHB009M.html?ref=rss">
 <title>兵庫知事、県議会4会派の辞職要求に応じず「補正予算成立が大事」</title>
 <link>https://www.asahi.com/articles/ASS9D2CXBS9DPIHB009M.html?ref=rss</link>
 <description></description>
 <dc:subject>政治</dc:subject>
 <dc:date>2024-09-12T16:23:24+09:00</dc:date>
</item>
</rdf:RDF>
