<?xml version="1.0" encoding="utf-8"?>
<rdf:RDF xmlns:rdf="http://www.w3.org/1999/02/22-rdf-syntax-ns#" xmlns="http://purl.org/rss/1.0/" xmlns:taxo="http://purl.org/rss/1.0/modules/taxonomy/" 	xmlns:dc="http://purl.org/dc/elements/1.1/" xmlns:syn="http://purl.org/rss/1.0/modules/syndication/">
<channel rdf:about="http://www3.asahi.com/">
 <title>社会 - 朝日新聞デジタル</title>
 <link>https://www.asahi.com/</link>
 <description>朝日新聞のニュースサイト、朝日新聞デジタルの一般社会ニュース、事件・事故、災害・交通情報、裁判、環境などのページです。</description>
 <dc:language>ja</dc:language>
 <dc:rights>Copyright 2024 Asahi Shimbun. All rights reserved. No reproduction or republication without written permission.</dc:rights>
 <dc:date>2024-03-01T20:00:00+09:00</dc:date>
 <dc:publisher>朝日新聞社</dc:publisher>
 <dc:creator>朝日新聞社</dc:creator>
 <syn:updatePeriod>hourly</syn:updatePeriod>
 <syn:updateFrequency>1</syn:updateFrequency>
 <syn:updateBase>2024-03-01T20:00:00+09:00</syn:updateBase>
 <items>
  <rdf:Seq>
   <rdf:li rdf:resource="https://www.asahi.com/articles/ASS316HCKS31OXIE00M.html?ref=rss"/>
   <rdf:li rdf:resource="https://www.asahi.com/articles/ASS316DPSS2XTIPE01M.html?ref=rss"/>
   <rdf:li rdf:resource="https://www.asahi.com/articles/ASS315H7HS2YOXIE03Y.html?ref=rss"/>
   <rdf:li rdf:resource="https://www.asahi.com/articles/ASS3167GMS2XOXIE01L.html?ref=rss"/>
   <rdf:li rdf:resource="https://www.asahi.com/articles/ASS315R2XS31UTFL00F.html?ref=rss"/>
   <rdf:li rdf:resource="https://www.asahi.com/articles/ASS3165WJS31PTIL00B.html?ref=rss"/>
   <rdf:li rdf:resource="https://www.asahi.com/articles/ASS316FYLS31PTLC020.html?ref=rss"/>
   <rdf:li rdf:resource="https://www.asahi.com/articles/ASS316D1HS31ULFA01P.html?ref=rss"/>
   <rdf:li rdf:resource="https://www.asahi.com/articles/ASS3161VJS31PXLB00C.html?ref=rss"/>
   <rdf:li rdf:resource="https://www.asahi.com/articles/ASS315WMHS31TPOB001.html?ref=rss"/>
   <rdf:li rdf:resource="https://www.asahi.com/articles/ASS3165L3S31OXIE01D.html?ref=rss"/>
   <rdf:li rdf:resource="https://www.asahi.com/articles/ASS3165TNS31IIPE006.html?ref=rss"/>
   <rdf:li rdf:resource="https://www.asahi.com/articles/ASS31658QS31PTIL00S.html?ref=rss"/>
   <rdf:li rdf:resource="https://www.asahi.com/articles/ASS3165ZRS31UTIL02W.html?ref=rss"/>
   <rdf:li rdf:resource="https://www.asahi.com/articles/ASS315WTSS31PTLC01D.html?ref=rss"/>
   <rdf:li rdf:resource="https://www.asahi.com/articles/ASS315D2BS31UTIL004.html?ref=rss"/>
   <rdf:li rdf:resource="https://www.asahi.com/articles/ASS2X4V5HS2VPTIL00H.html?ref=rss"/>
   <rdf:li rdf:resource="https://www.asahi.com/articles/ASS2Y6424S2VULOB01G.html?ref=rss"/>
   <rdf:li rdf:resource="https://www.asahi.com/articles/ASS314RPNS31OXIE016.html?ref=rss"/>
   <rdf:li rdf:resource="https://www.asahi.com/articles/ASS315QV5S31OXIE00B.html?ref=rss"/>
   <rdf:li rdf:resource="https://www.asahi.com/articles/ASS315J3NS31PLZB001.html?ref=rss"/>
   <rdf:li rdf:resource="https://www.asahi.com/articles/ASS315RWPS31OXIE028.html?ref=rss"/>
   <rdf:li rdf:resource="https://www.asahi.com/articles/ASS315JTQS31ULFA00Z.html?ref=rss"/>
   <rdf:li rdf:resource="https://www.asahi.com/articles/ASS2Y7754S2VPUUB00H.html?ref=rss"/>
   <rdf:li rdf:resource="https://www.asahi.com/articles/ASS315D7QS31PTJB00Q.html?ref=rss"/>
   <rdf:li rdf:resource="https://www.asahi.com/articles/ASS315401S31UTNB00J.html?ref=rss"/>
   <rdf:li rdf:resource="https://www.asahi.com/articles/ASS313W3FS31PIHB007.html?ref=rss"/>
   <rdf:li rdf:resource="https://www.asahi.com/articles/ASS2Y5VSMS2VUPQJ01C.html?ref=rss"/>
   <rdf:li rdf:resource="https://www.asahi.com/articles/ASS314VL6S31UHNB008.html?ref=rss"/>
   <rdf:li rdf:resource="https://www.asahi.com/articles/ASS314RCNS31UHNB00L.html?ref=rss"/>
   <rdf:li rdf:resource="https://www.asahi.com/articles/ASS314TYHS31UTIL00G.html?ref=rss"/>
   <rdf:li rdf:resource="https://www.asahi.com/articles/ASS314DKSS2WUTIL003.html?ref=rss"/>
   <rdf:li rdf:resource="https://www.asahi.com/articles/ASS314RWNS31OXIE00V.html?ref=rss"/>
   <rdf:li rdf:resource="https://www.asahi.com/articles/ASS2W4HZHS1WUCVL005.html?ref=rss"/>
   <rdf:li rdf:resource="https://www.asahi.com/articles/ASS3141R5S2WTIPE01L.html?ref=rss"/>
   <rdf:li rdf:resource="https://www.asahi.com/articles/ASS2X6SKNS2VUGTB00L.html?ref=rss"/>
   <rdf:li rdf:resource="https://www.asahi.com/articles/ASS314GRFS31TIPE009.html?ref=rss"/>
   <rdf:li rdf:resource="https://www.asahi.com/articles/ASS314GXXS31TIPE005.html?ref=rss"/>
   <rdf:li rdf:resource="https://www.asahi.com/articles/ASS3143XYS2YPIHB015.html?ref=rss"/>
   <rdf:li rdf:resource="https://www.asahi.com/articles/ASS2Y5DPDS2QPTIL00D.html?ref=rss"/>
  </rdf:Seq>
 </items>
</channel>
<item rdf:about="https://www.asahi.com/articles/ASS316HCKS31OXIE00M.html?ref=rss">
 <title>都立高の男女別定員、撤廃後初の合格発表　都教委「今後結果を検証」</title>
 <link>https://www.asahi.com/articles/ASS316HCKS31OXIE00M.html?ref=rss</link>
 <description></description>
 <dc:subject>社会</dc:subject>
 <dc:date>2024-03-01T20:00:00+09:00</dc:date>
</item>
<item rdf:about="https://www.asahi.com/articles/ASS316DPSS2XTIPE01M.html?ref=rss">
 <title>再生に向け寄付5千万円　飲食店街火災から2カ月、がれき撤去始まる</title>
 <link>https://www.asahi.com/articles/ASS316DPSS2XTIPE01M.html?ref=rss</link>
 <description></description>
 <dc:subject>社会</dc:subject>
 <dc:date>2024-03-01T19:50:27+09:00</dc:date>
</item>
<item rdf:about="https://www.asahi.com/articles/ASS315H7HS2YOXIE03Y.html?ref=rss">
 <title>危機感募らせる能登町長と珠洲市長　人口流出阻止へ「まず生活の場」</title>
 <link>https://www.asahi.com/articles/ASS315H7HS2YOXIE03Y.html?ref=rss</link>
 <description></description>
 <dc:subject>社会</dc:subject>
 <dc:date>2024-03-01T19:48:33+09:00</dc:date>
</item>
<item rdf:about="https://www.asahi.com/articles/ASS3167GMS2XOXIE01L.html?ref=rss">
 <title>石川6市町から1400人超転出　地震2カ月、人口流出に拍車の懸念</title>
 <link>https://www.asahi.com/articles/ASS3167GMS2XOXIE01L.html?ref=rss</link>
 <description></description>
 <dc:subject>社会</dc:subject>
 <dc:date>2024-03-01T19:46:38+09:00</dc:date>
</item>
<item rdf:about="https://www.asahi.com/articles/ASS315R2XS31UTFL00F.html?ref=rss">
 <title>「満足度No.1」根拠なし　「イモトのWiFi」の広告に措置命令</title>
 <link>https://www.asahi.com/articles/ASS315R2XS31UTFL00F.html?ref=rss</link>
 <description></description>
 <dc:subject>社会</dc:subject>
 <dc:date>2024-03-01T19:44:37+09:00</dc:date>
</item>
<item rdf:about="https://www.asahi.com/articles/ASS3165WJS31PTIL00B.html?ref=rss">
 <title>能登半島を出る18歳、残る18歳　卒業式で贈られた言葉と決意</title>
 <link>https://www.asahi.com/articles/ASS3165WJS31PTIL00B.html?ref=rss</link>
 <description></description>
 <dc:subject>社会</dc:subject>
 <dc:date>2024-03-01T19:32:52+09:00</dc:date>
</item>
<item rdf:about="https://www.asahi.com/articles/ASS316FYLS31PTLC020.html?ref=rss">
 <title>能登の高校卒業生にサプライズ、一青窈さんと歌って「もらい泣き」</title>
 <link>https://www.asahi.com/articles/ASS316FYLS31PTLC020.html?ref=rss</link>
 <description></description>
 <dc:subject>社会</dc:subject>
 <dc:date>2024-03-01T19:30:52+09:00</dc:date>
</item>
<item rdf:about="https://www.asahi.com/articles/ASS316D1HS31ULFA01P.html?ref=rss">
 <title>ビッグモーターを書類送検　違法残業の疑い、最長月116時間超</title>
 <link>https://www.asahi.com/articles/ASS316D1HS31ULFA01P.html?ref=rss</link>
 <description></description>
 <dc:subject>社会</dc:subject>
 <dc:date>2024-03-01T19:30:02+09:00</dc:date>
</item>
<item rdf:about="https://www.asahi.com/articles/ASS3161VJS31PXLB00C.html?ref=rss">
 <title>「紀州のドン・ファン」遺産の行方　遺言の無効確認訴訟、6月に判決</title>
 <link>https://www.asahi.com/articles/ASS3161VJS31PXLB00C.html?ref=rss</link>
 <description></description>
 <dc:subject>社会</dc:subject>
 <dc:date>2024-03-01T19:30:00+09:00</dc:date>
</item>
<item rdf:about="https://www.asahi.com/articles/ASS315WMHS31TPOB001.html?ref=rss">
 <title>復帰後最大の不発弾爆発から半世紀　沖縄で追悼行事</title>
 <link>https://www.asahi.com/articles/ASS315WMHS31TPOB001.html?ref=rss</link>
 <description></description>
 <dc:subject>社会</dc:subject>
 <dc:date>2024-03-01T19:30:00+09:00</dc:date>
</item>
<item rdf:about="https://www.asahi.com/articles/ASS3165L3S31OXIE01D.html?ref=rss">
 <title>オーバーツーリズム対策、「入山税」の導入検討　和歌山・高野町</title>
 <link>https://www.asahi.com/articles/ASS3165L3S31OXIE01D.html?ref=rss</link>
 <description></description>
 <dc:subject>社会</dc:subject>
 <dc:date>2024-03-01T19:30:00+09:00</dc:date>
</item>
<item rdf:about="https://www.asahi.com/articles/ASS3165TNS31IIPE006.html?ref=rss">
 <title>愛媛からきた「オス」ライオン、実はメスでした　札幌市円山動物園</title>
 <link>https://www.asahi.com/articles/ASS3165TNS31IIPE006.html?ref=rss</link>
 <description></description>
 <dc:subject>社会</dc:subject>
 <dc:date>2024-03-01T19:30:00+09:00</dc:date>
</item>
<item rdf:about="https://www.asahi.com/articles/ASS31658QS31PTIL00S.html?ref=rss">
 <title>「検察権、適正に行使する」　小弓場・新検事正が着任　大阪地検</title>
 <link>https://www.asahi.com/articles/ASS31658QS31PTIL00S.html?ref=rss</link>
 <description></description>
 <dc:subject>社会</dc:subject>
 <dc:date>2024-03-01T19:06:49+09:00</dc:date>
</item>
<item rdf:about="https://www.asahi.com/articles/ASS3165ZRS31UTIL02W.html?ref=rss">
 <title>辺野古の「代執行訴訟」、沖縄県の敗訴確定　埋め立て工事継続へ</title>
 <link>https://www.asahi.com/articles/ASS3165ZRS31UTIL02W.html?ref=rss</link>
 <description></description>
 <dc:subject>社会</dc:subject>
 <dc:date>2024-03-01T18:53:57+09:00</dc:date>
</item>
<item rdf:about="https://www.asahi.com/articles/ASS315WTSS31PTLC01D.html?ref=rss">
 <title>一変した景色、でも…「仲間の存在胸に前へ」　能登高から47人卒業</title>
 <link>https://www.asahi.com/articles/ASS315WTSS31PTLC01D.html?ref=rss</link>
 <description></description>
 <dc:subject>社会</dc:subject>
 <dc:date>2024-03-01T18:36:38+09:00</dc:date>
</item>
<item rdf:about="https://www.asahi.com/articles/ASS315D2BS31UTIL004.html?ref=rss">
 <title>東京消防庁の一日消防署長に藤本美貴さん　ライブ119使い救助訓練</title>
 <link>https://www.asahi.com/articles/ASS315D2BS31UTIL004.html?ref=rss</link>
 <description></description>
 <dc:subject>社会</dc:subject>
 <dc:date>2024-03-01T18:30:00+09:00</dc:date>
</item>
<item rdf:about="https://www.asahi.com/articles/ASS2X4V5HS2VPTIL00H.html?ref=rss">
 <title>原爆資料館で開いた原子力博覧会　ビキニ事件の「機密」と米国の思惑</title>
 <link>https://www.asahi.com/articles/ASS2X4V5HS2VPTIL00H.html?ref=rss</link>
 <description></description>
 <dc:subject>社会</dc:subject>
 <dc:date>2024-03-01T18:00:00+09:00</dc:date>
</item>
<item rdf:about="https://www.asahi.com/articles/ASS2Y6424S2VULOB01G.html?ref=rss">
 <title>70年前の核実験は「マグロのまち」にも大打撃　三崎で150隻被曝</title>
 <link>https://www.asahi.com/articles/ASS2Y6424S2VULOB01G.html?ref=rss</link>
 <description></description>
 <dc:subject>社会</dc:subject>
 <dc:date>2024-03-01T18:00:00+09:00</dc:date>
</item>
<item rdf:about="https://www.asahi.com/articles/ASS314RPNS31OXIE016.html?ref=rss">
 <title>「もふもふ」は期間限定です…ゴマフアザラシの赤ちゃん誕生、公開中</title>
 <link>https://www.asahi.com/articles/ASS314RPNS31OXIE016.html?ref=rss</link>
 <description></description>
 <dc:subject>社会</dc:subject>
 <dc:date>2024-03-01T18:00:00+09:00</dc:date>
</item>
<item rdf:about="https://www.asahi.com/articles/ASS315QV5S31OXIE00B.html?ref=rss">
 <title>大変な状況は「大きく変わる機会」　輪島高校、100キロ離れ卒業式</title>
 <link>https://www.asahi.com/articles/ASS315QV5S31OXIE00B.html?ref=rss</link>
 <description></description>
 <dc:subject>社会</dc:subject>
 <dc:date>2024-03-01T17:52:49+09:00</dc:date>
</item>
<item rdf:about="https://www.asahi.com/articles/ASS315J3NS31PLZB001.html?ref=rss">
 <title>京アニ事件の碑、宇治市の公園に設置へ　市長「事件に思いはせて」</title>
 <link>https://www.asahi.com/articles/ASS315J3NS31PLZB001.html?ref=rss</link>
 <description></description>
 <dc:subject>社会</dc:subject>
 <dc:date>2024-03-01T17:44:48+09:00</dc:date>
</item>
<item rdf:about="https://www.asahi.com/articles/ASS315RWPS31OXIE028.html?ref=rss">
 <title>「私たちの思い、伝えたい」卒業生12人全員で答辞にのぞんだ門前高</title>
 <link>https://www.asahi.com/articles/ASS315RWPS31OXIE028.html?ref=rss</link>
 <description></description>
 <dc:subject>社会</dc:subject>
 <dc:date>2024-03-01T17:29:42+09:00</dc:date>
</item>
<item rdf:about="https://www.asahi.com/articles/ASS315JTQS31ULFA00Z.html?ref=rss">
 <title>能登の被災者支援プラス300万円　政府が予備費１千億円超決定</title>
 <link>https://www.asahi.com/articles/ASS315JTQS31ULFA00Z.html?ref=rss</link>
 <description></description>
 <dc:subject>社会</dc:subject>
 <dc:date>2024-03-01T17:23:25+09:00</dc:date>
</item>
<item rdf:about="https://www.asahi.com/articles/ASS2Y7754S2VPUUB00H.html?ref=rss">
 <title>指は5本ないとダメ？　感じた違和感を描き、戯曲コンテスト最優秀　</title>
 <link>https://www.asahi.com/articles/ASS2Y7754S2VPUUB00H.html?ref=rss</link>
 <description></description>
 <dc:subject>社会</dc:subject>
 <dc:date>2024-03-01T17:00:00+09:00</dc:date>
</item>
<item rdf:about="https://www.asahi.com/articles/ASS315D7QS31PTJB00Q.html?ref=rss">
 <title>「私は石川県民のために」飯田高校から89人卒業　式典で黙禱捧げる</title>
 <link>https://www.asahi.com/articles/ASS315D7QS31PTJB00Q.html?ref=rss</link>
 <description></description>
 <dc:subject>社会</dc:subject>
 <dc:date>2024-03-01T16:27:15+09:00</dc:date>
</item>
<item rdf:about="https://www.asahi.com/articles/ASS315401S31UTNB00J.html?ref=rss">
 <title>稲川会総本部を初めて捜索　殺人容疑で傘下組長の逮捕受け　埼玉県警</title>
 <link>https://www.asahi.com/articles/ASS315401S31UTNB00J.html?ref=rss</link>
 <description></description>
 <dc:subject>社会</dc:subject>
 <dc:date>2024-03-01T16:00:00+09:00</dc:date>
</item>
<item rdf:about="https://www.asahi.com/articles/ASS313W3FS31PIHB007.html?ref=rss">
 <title>8年前の男性切断遺体、殺人容疑で男を書類送検　中国で無期懲役判決</title>
 <link>https://www.asahi.com/articles/ASS313W3FS31PIHB007.html?ref=rss</link>
 <description></description>
 <dc:subject>社会</dc:subject>
 <dc:date>2024-03-01T15:32:06+09:00</dc:date>
</item>
<item rdf:about="https://www.asahi.com/articles/ASS2Y5VSMS2VUPQJ01C.html?ref=rss">
 <title>食べログの点数評価は公正か　優越的地位の乱用めぐり揺れる司法判断</title>
 <link>https://www.asahi.com/articles/ASS2Y5VSMS2VUPQJ01C.html?ref=rss</link>
 <description></description>
 <dc:subject>社会</dc:subject>
 <dc:date>2024-03-01T15:30:00+09:00</dc:date>
</item>
<item rdf:about="https://www.asahi.com/articles/ASS314VL6S31UHNB008.html?ref=rss">
 <title>「能登は決して負けません」　校舎使えない穴水高校、34人が巣立ち</title>
 <link>https://www.asahi.com/articles/ASS314VL6S31UHNB008.html?ref=rss</link>
 <description></description>
 <dc:subject>社会</dc:subject>
 <dc:date>2024-03-01T15:25:33+09:00</dc:date>
</item>
<item rdf:about="https://www.asahi.com/articles/ASS314RCNS31UHNB00L.html?ref=rss">
 <title>北関東道で車4台絡む事故　1人死亡、1人重体　逆走車両が衝突か</title>
 <link>https://www.asahi.com/articles/ASS314RCNS31UHNB00L.html?ref=rss</link>
 <description></description>
 <dc:subject>社会</dc:subject>
 <dc:date>2024-03-01T15:15:03+09:00</dc:date>
</item>
<item rdf:about="https://www.asahi.com/articles/ASS314TYHS31UTIL00G.html?ref=rss">
 <title>「万死に値する」　柿沢前議員が法廷で謝罪　検察側は懲役2年求刑</title>
 <link>https://www.asahi.com/articles/ASS314TYHS31UTIL00G.html?ref=rss</link>
 <description></description>
 <dc:subject>社会</dc:subject>
 <dc:date>2024-03-01T15:06:22+09:00</dc:date>
</item>
<item rdf:about="https://www.asahi.com/articles/ASS314DKSS2WUTIL003.html?ref=rss">
 <title>無許可接待の疑い、メンコン経営者ら逮捕　記者が入って見た実態とは</title>
 <link>https://www.asahi.com/articles/ASS314DKSS2WUTIL003.html?ref=rss</link>
 <description></description>
 <dc:subject>社会</dc:subject>
 <dc:date>2024-03-01T15:00:00+09:00</dc:date>
</item>
<item rdf:about="https://www.asahi.com/articles/ASS314RWNS31OXIE00V.html?ref=rss">
 <title>上信越道で20～30台絡む事故　1人死亡、10人以上けが</title>
 <link>https://www.asahi.com/articles/ASS314RWNS31OXIE00V.html?ref=rss</link>
 <description></description>
 <dc:subject>社会</dc:subject>
 <dc:date>2024-03-01T14:50:03+09:00</dc:date>
</item>
<item rdf:about="https://www.asahi.com/articles/ASS2W4HZHS1WUCVL005.html?ref=rss">
 <title>「後悔は永遠」　ソプラノ歌手・荒牧小百合さんを変えた娘のことば</title>
 <link>https://www.asahi.com/articles/ASS2W4HZHS1WUCVL005.html?ref=rss</link>
 <description></description>
 <dc:subject>社会</dc:subject>
 <dc:date>2024-03-01T14:30:00+09:00</dc:date>
</item>
<item rdf:about="https://www.asahi.com/articles/ASS3141R5S2WTIPE01L.html?ref=rss">
 <title>福岡市地下鉄七隈線23日にダイヤ改正　増便で最短3分おき運行に</title>
 <link>https://www.asahi.com/articles/ASS3141R5S2WTIPE01L.html?ref=rss</link>
 <description></description>
 <dc:subject>社会</dc:subject>
 <dc:date>2024-03-01T14:30:00+09:00</dc:date>
</item>
<item rdf:about="https://www.asahi.com/articles/ASS2X6SKNS2VUGTB00L.html?ref=rss">
 <title>同級生から「近づくな放射線」　原発避難者の悲しみや怒りを映像で</title>
 <link>https://www.asahi.com/articles/ASS2X6SKNS2VUGTB00L.html?ref=rss</link>
 <description></description>
 <dc:subject>社会</dc:subject>
 <dc:date>2024-03-01T14:00:00+09:00</dc:date>
</item>
<item rdf:about="https://www.asahi.com/articles/ASS314GRFS31TIPE009.html?ref=rss">
 <title>2024年問題対策で最終便を大幅繰り上げ　西鉄バス「苦渋の決断」</title>
 <link>https://www.asahi.com/articles/ASS314GRFS31TIPE009.html?ref=rss</link>
 <description></description>
 <dc:subject>社会</dc:subject>
 <dc:date>2024-03-01T13:49:58+09:00</dc:date>
</item>
<item rdf:about="https://www.asahi.com/articles/ASS314GXXS31TIPE005.html?ref=rss">
 <title>教員が出願ミス、3人が志望高校受験できず　「提出期限を勘違い」</title>
 <link>https://www.asahi.com/articles/ASS314GXXS31TIPE005.html?ref=rss</link>
 <description></description>
 <dc:subject>社会</dc:subject>
 <dc:date>2024-03-01T13:44:00+09:00</dc:date>
</item>
<item rdf:about="https://www.asahi.com/articles/ASS3143XYS2YPIHB015.html?ref=rss">
 <title>「これからも帰ってくる」門前高校12人の旅立ち、能登の高3卒業式</title>
 <link>https://www.asahi.com/articles/ASS3143XYS2YPIHB015.html?ref=rss</link>
 <description></description>
 <dc:subject>社会</dc:subject>
 <dc:date>2024-03-01T13:30:00+09:00</dc:date>
</item>
<item rdf:about="https://www.asahi.com/articles/ASS2Y5DPDS2QPTIL00D.html?ref=rss">
 <title>がれきの下のエプロン姿　返事ない母助けてくれた隊員に涙と感謝と</title>
 <link>https://www.asahi.com/articles/ASS2Y5DPDS2QPTIL00D.html?ref=rss</link>
 <description></description>
 <dc:subject>社会</dc:subject>
 <dc:date>2024-03-01T13:15:26+09:00</dc:date>
</item>
</rdf:RDF>
