<?xml version="1.0" encoding="utf-8"?>
<rdf:RDF xmlns:rdf="http://www.w3.org/1999/02/22-rdf-syntax-ns#" xmlns="http://purl.org/rss/1.0/" xmlns:taxo="http://purl.org/rss/1.0/modules/taxonomy/" 	xmlns:dc="http://purl.org/dc/elements/1.1/" xmlns:syn="http://purl.org/rss/1.0/modules/syndication/">
<channel rdf:about="http://www3.asahi.com/">
 <title>政治 - 朝日新聞デジタル</title>
 <link>https://www.asahi.com/</link>
 <description>朝日新聞のニュースサイト、朝日新聞デジタルの一般政治ニュース、国政、地方政治内閣支持率などに関するページです。</description>
 <dc:language>ja</dc:language>
 <dc:rights>Copyright 2023 Asahi Shimbun. All rights reserved. No reproduction or republication without written permission.</dc:rights>
 <dc:date>2023-10-30T07:15:00+09:00</dc:date>
 <dc:publisher>朝日新聞社</dc:publisher>
 <dc:creator>朝日新聞社</dc:creator>
 <syn:updatePeriod>hourly</syn:updatePeriod>
 <syn:updateFrequency>1</syn:updateFrequency>
 <syn:updateBase>2023-10-30T07:15:00+09:00</syn:updateBase>
 <items>
  <rdf:Seq>
   <rdf:li rdf:resource="https://www.asahi.com/articles/ASRBY2TQRRBKUPQJ00C.html?ref=rss"/>
   <rdf:li rdf:resource="https://www.asahi.com/articles/ASRBN20RKRB8UZPS001.html?ref=rss"/>
   <rdf:li rdf:resource="https://www.asahi.com/articles/ASRBY52VSRBVOXIE047.html?ref=rss"/>
   <rdf:li rdf:resource="https://www.asahi.com/articles/ASRBY4V62RBYUTFK008.html?ref=rss"/>
   <rdf:li rdf:resource="https://www.asahi.com/articles/ASRBY4D0VRBYUTFK006.html?ref=rss"/>
   <rdf:li rdf:resource="https://www.asahi.com/articles/ASRBX64JPRBSOXIE00X.html?ref=rss"/>
   <rdf:li rdf:resource="https://www.asahi.com/articles/ASRBW6JQXRBWULFA013.html?ref=rss"/>
  </rdf:Seq>
 </items>
</channel>
<item rdf:about="https://www.asahi.com/articles/ASRBY2TQRRBKUPQJ00C.html?ref=rss">
 <title>副大臣・政務官、女性ゼロ 「メディアは騒ぐかも」　驚きの適材適所</title>
 <link>https://www.asahi.com/articles/ASRBY2TQRRBKUPQJ00C.html?ref=rss</link>
 <description></description>
 <dc:subject>政治</dc:subject>
 <dc:date>2023-10-30T07:15:00+09:00</dc:date>
</item>
<item rdf:about="https://www.asahi.com/articles/ASRBN20RKRB8UZPS001.html?ref=rss">
 <title>退陣のきっかけはリクルート事件　政治不信が極度に高まった竹下内閣</title>
 <link>https://www.asahi.com/articles/ASRBN20RKRB8UZPS001.html?ref=rss</link>
 <description></description>
 <dc:subject>政治</dc:subject>
 <dc:date>2023-10-30T05:00:00+09:00</dc:date>
</item>
<item rdf:about="https://www.asahi.com/articles/ASRBY52VSRBVOXIE047.html?ref=rss">
 <title>万博に向けたライドシェア導入は「公共の福祉」？　大阪府・市が検討</title>
 <link>https://www.asahi.com/articles/ASRBY52VSRBVOXIE047.html?ref=rss</link>
 <description></description>
 <dc:subject>政治</dc:subject>
 <dc:date>2023-10-29T18:00:00+09:00</dc:date>
</item>
<item rdf:about="https://www.asahi.com/articles/ASRBY4V62RBYUTFK008.html?ref=rss">
 <title>自民・萩生田政調会長、「定額減税」に2年以上の可能性言及</title>
 <link>https://www.asahi.com/articles/ASRBY4V62RBYUTFK008.html?ref=rss</link>
 <description></description>
 <dc:subject>政治</dc:subject>
 <dc:date>2023-10-29T15:00:00+09:00</dc:date>
</item>
<item rdf:about="https://www.asahi.com/articles/ASRBY4D0VRBYUTFK006.html?ref=rss">
 <title>公明山口氏、年内の衆院解散は「日程窮屈」　予算審議や外交日程考慮</title>
 <link>https://www.asahi.com/articles/ASRBY4D0VRBYUTFK006.html?ref=rss</link>
 <description></description>
 <dc:subject>政治</dc:subject>
 <dc:date>2023-10-29T13:21:43+09:00</dc:date>
</item>
<item rdf:about="https://www.asahi.com/articles/ASRBX64JPRBSOXIE00X.html?ref=rss">
 <title>尾形大作氏を支部長から解任　主導した自民党本部に地元大阪から批判</title>
 <link>https://www.asahi.com/articles/ASRBX64JPRBSOXIE00X.html?ref=rss</link>
 <description></description>
 <dc:subject>政治</dc:subject>
 <dc:date>2023-10-29T09:00:00+09:00</dc:date>
</item>
<item rdf:about="https://www.asahi.com/articles/ASRBW6JQXRBWULFA013.html?ref=rss">
 <title>自衛隊とフィリピン軍、訓練円滑化へ　来月首脳会談、中国念頭に協力</title>
 <link>https://www.asahi.com/articles/ASRBW6JQXRBWULFA013.html?ref=rss</link>
 <description></description>
 <dc:subject>政治</dc:subject>
 <dc:date>2023-10-28T08:30:00+09:00</dc:date>
</item>
</rdf:RDF>
